dcarte/.DS_Store
dcarte/__init__.py
dcarte/__version__.py
dcarte/_delete.py
dcarte/config.py
dcarte/derived/.DS_Store
dcarte/derived/__init__.py
dcarte/derived/base.py
dcarte/derived/bed_occupancy.py
dcarte/derived/weekly_profile.py
dcarte/domains.py
dcarte/download.py
dcarte/legacy/legacy.py
dcarte/load.py
dcarte/local.py
dcarte/minder.py
dcarte/source_yaml/care.yaml
dcarte/source_yaml/lookup.yaml
dcarte/source_yaml/raw.yaml
dcarte/update.py
dcarte/utils.py
dcarte-0.4.17.dist-info/WHEEL
dcarte-0.4.17.dist-info/METADATA
dcarte-0.4.17.dist-info/RECORD
