Metadata-Version: 2.1
Name: dcarte
Version: 0.4.17
Summary: DCARTE is a dataset ingestion tool from DCARTE UK-DRI CAre Research and TEchnology
Home-page: https://github.com/esoreq/dcarte
Author: eyal soreq
Requires-Python: >=3.8,<=3.12
Classifier: Programming Language :: Python :: 3
Classifier: Programming Language :: Python :: 3.8
Classifier: Programming Language :: Python :: 3.9
Classifier: Programming Language :: Python :: 3.10
Classifier: Programming Language :: Python :: 3.11
Requires-Dist: PyYAML (>=5.5)
Requires-Dist: deepdiff (>=5.7.0,<6.0.0)
Requires-Dist: numpy (>=1.19.2)
Requires-Dist: pandas (>=2.0.0)
Requires-Dist: pyarrow (>=3.0.0,<=13.0.0)
Requires-Dist: python-dateutil (>=2.8.2,<3.0.0)
Requires-Dist: requests (>=2.26.0,<3.0.0)
Requires-Dist: scipy (>=1.7.3,<2.0.0)
Requires-Dist: tqdm (>=4.62.3,<5.0.0)
Project-URL: Documentation, https://esoreq.github.io/dcarte/_build/html/index.html
Project-URL: Repository, https://github.com/esoreq/dcarte
